LICENSE
MANIFEST.in
README.md
pyproject.toml
requirements.txt
setup.py
tarn/__init__.py
tarn/__version__.py
tarn/compat.py
tarn/config.py
tarn/digest.py
tarn/exceptions.py
tarn/functional.py
tarn/interface.py
tarn/serializers.py
tarn/utils.py
tarn.egg-info/PKG-INFO
tarn.egg-info/SOURCES.txt
tarn.egg-info/dependency_links.txt
tarn.egg-info/requires.txt
tarn.egg-info/top_level.txt
tarn/cache/__init__.py
tarn/cache/compat.py
tarn/cache/pickler.py
tarn/cache/serializers.py
tarn/local/__init__.py
tarn/local/disk.py
tarn/location/__init__.py
tarn/location/fanout.py
tarn/location/interface.py
tarn/location/levels.py
tarn/location/nginx.py
tarn/location/redis.py
tarn/location/s3.py
tarn/location/small.py
tarn/location/disk_dict/__init__.py
tarn/location/disk_dict/config.py
tarn/location/disk_dict/location.py
tarn/location/ssh/__init__.py
tarn/location/ssh/interface.py
tarn/location/ssh/scp.py
tarn/location/ssh/sftp.py
tarn/pickler/__init__.py
tarn/pickler/compat.py
tarn/pickler/interface.py
tarn/pool/__init__.py
tarn/pool/hash_key.py
tarn/pool/pickle_key.py
tarn/remote/__init__.py
tarn/remote/http.py
tarn/remote/ssh.py
tarn/tools/__init__.py
tarn/tools/labels.py
tarn/tools/locker.py
tarn/tools/size.py
tarn/tools/usage.py