Metadata-Version: 2.1
Name: tarn
Version: 0.12.0
Summary: A generic framework for key-value storage
Home-page: https://github.com/neuro-ml/tarn
Author: Max
Author-email: max@ira-labs.com
License: UNKNOWN
Download-URL: https://github.com/neuro-ml/tarn/archive/v0.12.0.tar.gz
Keywords: storage,cache,invalidation
Platform: UNKNOWN
Classifier: Development Status :: 4 - Beta
Classifier: License :: OSI Approved :: Apache Software License
Classifier: Programming Language :: Python :: 3
Classifier: Programming Language :: Python :: 3.6
Classifier: Programming Language :: Python :: 3.7
Classifier: Programming Language :: Python :: 3.8
Classifier: Programming Language :: Python :: 3.9
Classifier: Programming Language :: Python :: 3.10
Classifier: Programming Language :: Python :: 3.11
Classifier: Programming Language :: Python :: 3 :: Only
Requires-Python: >=3.7
License-File: LICENSE
